openapi_python_generator/__init__.py
openapi_python_generator/__main__.py
openapi_python_generator/common.py
openapi_python_generator/generate_data.py
openapi_python_generator/language_converters/__init__.py
openapi_python_generator/language_converters/python/__init__.py
openapi_python_generator/language_converters/python/api_config_generator.py
openapi_python_generator/language_converters/python/common.py
openapi_python_generator/language_converters/python/generator.py
openapi_python_generator/language_converters/python/jinja_config.py
openapi_python_generator/language_converters/python/model_generator.py
openapi_python_generator/language_converters/python/service_generator.py
openapi_python_generator/language_converters/python/templates/aiohttp.jinja2
openapi_python_generator/language_converters/python/templates/apiconfig.jinja2
openapi_python_generator/language_converters/python/templates/apiconfig_pydantic_2.jinja2
openapi_python_generator/language_converters/python/templates/enum.jinja2
openapi_python_generator/language_converters/python/templates/httpx.jinja2
openapi_python_generator/language_converters/python/templates/models.jinja2
openapi_python_generator/language_converters/python/templates/models_pydantic_2.jinja2
openapi_python_generator/language_converters/python/templates/requests.jinja2
openapi_python_generator/language_converters/python/templates/service.jinja2
openapi_python_generator/models.py
openapi_python_generator/parsers/__init__.py
openapi_python_generator/parsers/openapi_30.py
openapi_python_generator/parsers/openapi_31.py
openapi_python_generator/py.typed
openapi_python_generator/version_detector.py
openapi_python_generator-2.1.2.dist-info/LICENSE
openapi_python_generator-2.1.2.dist-info/WHEEL
openapi_python_generator-2.1.2.dist-info/entry_points.txt
openapi_python_generator-2.1.2.dist-info/METADATA
openapi_python_generator-2.1.2.dist-info/RECORD
