Metadata-Version: 2.1
Name: openapi-python-generator
Version: 2.1.2
Summary: Openapi Python Generator
Home-page: https://github.com/MarcoMuellner/openapi-python-generator
License: MIT
Keywords: OpenAPI,Generator,Python,async
Author: Marco Müllner
Author-email: muellnermarco@gmail.com
Requires-Python: >=3.9,<4.0
Classifier: Development Status :: 3 - Alpha
Classifier: License :: OSI Approved :: MIT License
Classifier: Programming Language :: Python :: 3
Classifier: Programming Language :: Python :: 3.9
Classifier: Programming Language :: Python :: 3.10
Classifier: Programming Language :: Python :: 3.11
Requires-Dist: Jinja2 (>=3.1.2,<4.0.0)
Requires-Dist: black (>=21.10b0)
Requires-Dist: click (>=8.1.3,<9.0.0)
Requires-Dist: httpx[all] (>=0.28.0,<0.29.0)
Requires-Dist: importlib-metadata (>=8.7.0,<9.0.0)
Requires-Dist: isort (>=5.10.1)
Requires-Dist: openapi-pydantic (>=0.5.1,<0.6.0)
Requires-Dist: orjson (>=3.9.15,<4.0.0)
Requires-Dist: pydantic (>=2.10.2,<3.0.0)
Requires-Dist: pyyaml (>=6.0.2,<7.0.0)
Project-URL: Changelog, https://github.com/MarcoMuellner/openapi-python-generator/releases
Project-URL: Documentation, https://openapi-python-generator.readthedocs.io
Project-URL: Repository, https://github.com/MarcoMuellner/openapi-python-generator
